wechat_enterprise/__init__.py
wechat_enterprise/wechat_enterprise.py
wechat_enterprise_sdk-1.0.1.dist-info/LICENSE
wechat_enterprise_sdk-1.0.1.dist-info/METADATA
wechat_enterprise_sdk-1.0.1.dist-info/WHEEL
wechat_enterprise_sdk-1.0.1.dist-info/top_level.txt
wechat_enterprise_sdk-1.0.1.dist-info/RECORD
