Metadata-Version: 2.1
Name: wechat_enterprise_sdk
Version: 1.0.1
Home-page: https://github.com/somenzz/wechat_enterprise
Author: somenzz
Author-email: somenzz@163.com
License: MIT
Keywords: python wechat enterprise,wechat_enterprise,send message
Classifier: Development Status :: 3 - Alpha
Classifier: Intended Audience :: Developers
Classifier: License :: OSI Approved :: MIT License
Classifier: Operating System :: OS Independent
Classifier: Programming Language :: Python
Classifier: Programming Language :: Python :: 3
Classifier: Topic :: Software Development
Classifier: Topic :: Software Development :: Libraries :: Python Modules
Classifier: Topic :: Utilities
License-File: LICENSE
Requires-Dist: requests
Requires-Dist: requests-toolbelt
